paetools/__init__.py
paetools-0.1.20250909.dist-info/METADATA
paetools-0.1.20250909.dist-info/WHEEL
paetools-0.1.20250909.dist-info/entry_points.txt
paetools-0.1.20250909.dist-info/RECORD
