Metadata-Version: 2.4
Name: paetools
Version: 0.1.20250909
Summary: Add your description here
Author-email: Yanguan02 <ligengyuan@h-partners.com>
Requires-Python: >=3.11
Requires-Dist: dataset-tool
Requires-Dist: onnx-tool
